{
  "timestamp": "2025-11-07T01:51:39.271942",
  "service": "parsing-rules",
  "team": "teamb",
  "resources": [
    {
      "id": "70d09d8e-3d24-4410-8321-8d4d31d6abfb",
      "name": "Severity Rules",
      "description": "",
      "creator": "organisations-service",
      "enabled": true,
      "hidden": false,
      "ruleMatchers": [],
      "ruleSubgroups": [
        {
          "id": "fda88c4d-8c35-4d88-937b-83e6d5b16949",
          "rules": [
            {
              "id": "88786f4a-628c-454e-9996-e553a84e5f00",
              "name": "Severity Rule",
              "description": "Look for default severity text",
              "sourceField": "text",
              "parameters": {
                "extractParameters": {
                  "rule": "\\b(?P<severity>DEBUG|TRACE|INFO|WARN|ERROR|FATAL|EXCEPTION|[Dd]ebug|[Tt]race|[Ii]nfo|[Ww]arn|[Ee]rror|[Ff]atal|[Ee]xception)\\b"
                }
              },
              "enabled": true,
              "order": 1
            }
          ],
          "enabled": true,
          "order": 1
        }
      ],
      "order": 1
    }
  ],
  "count": 1,
  "resource_identifiers": [
    "Severity Rules"
  ]
}