{
  "dashboard": {
    "annotations": {
      "list": [
        {
          "builtIn": 1,
          "datasource": {
            "type": "grafana",
            "uid": "-- Grafana --"
          },
          "enable": true,
          "hide": true,
          "iconColor": "rgba(0, 211, 255, 1)",
          "name": "Annotations & Alerts",
          "target": {
            "limit": 100,
            "matchAny": false,
            "tags": [],
            "type": "dashboard"
          },
          "type": "dashboard"
        }
      ]
    },
    "editable": true,
    "fiscalYearStartMonth": 0,
    "graphTooltip": 0,
    "links": [],
    "liveNow": false,
    "maxDataPoints": 3000,
    "panels": [
      {
        "datasource": {
          "type": "prometheus",
          "uid": "-FPV4La7z"
        },
        "fieldConfig": {
          "defaults": {
            "color": {
              "mode": "palette-classic"
            },
            "custom": {
              "axisCenteredZero": false,
              "axisColorMode": "text",
              "axisLabel": "",
              "axisPlacement": "auto",
              "barAlignment": 0,
              "drawStyle": "line",
              "fillOpacity": 0,
              "gradientMode": "none",
              "hideFrom": {
                "legend": false,
                "tooltip": false,
                "viz": false
              },
              "lineInterpolation": "linear",
              "lineWidth": 1,
              "pointSize": 5,
              "scaleDistribution": {
                "type": "linear"
              },
              "showPoints": "auto",
              "spanNulls": false,
              "stacking": {
                "group": "A",
                "mode": "none"
              },
              "thresholdsStyle": {
                "mode": "off"
              }
            },
            "mappings": [],
            "thresholds": {
              "mode": "absolute",
              "steps": [
                {
                  "color": "green",
                  "value": null
                },
                {
                  "color": "red",
                  "value": 80
                }
              ]
            }
          },
          "overrides": []
        },
        "gridPos": {
          "h": 8,
          "w": 12,
          "x": 0,
          "y": 0
        },
        "id": 1,
        "maxDataPoints": 3000,
        "options": {
          "legend": {
            "calcs": [],
            "displayMode": "list",
            "placement": "bottom",
            "showLegend": true
          },
          "tooltip": {
            "mode": "single",
            "sort": "none"
          }
        },
        "pluginVersion": "9.3.2",
        "targets": [
          {
            "datasource": {
              "type": "prometheus",
              "uid": "-FPV4La7z"
            },
            "editorMode": "code",
            "exemplar": false,
            "expr": "(sum(kube_pod_status_ready{source_cluster=~\"$cluster\", pod=~'fluentd.*'}))",
            "instant": true,
            "key": "Q-e15fa9c0-f6c3-448f-acaf-28823b85b784-0",
            "legendFormat": "__auto",
            "range": true,
            "refId": "A"
          }
        ],
        "title": "Fluentd Deployment",
        "type": "timeseries"
      }
    ],
    "refresh": false,
    "schemaVersion": 37,
    "style": "dark",
    "tags": [],
    "templating": {
      "list": [
        {
          "current": {
            "selected": false,
            "text": "hs-eks-prod5-api-apse1",
            "value": "hs-eks-prod5-api-apse1"
          },
          "datasource": {
            "type": "prometheus",
            "uid": "-FPV4La7z"
          },
          "definition": "label_values(kube_pod_container_info, source_cluster)",
          "description": "",
          "hide": 0,
          "includeAll": false,
          "label": "cluster",
          "multi": false,
          "name": "cluster",
          "options": [],
          "query": {
            "query": "label_values(kube_pod_container_info, source_cluster)",
            "refId": "StandardVariableQuery"
          },
          "refresh": 2,
          "regex": "",
          "skipUrlSync": false,
          "sort": 0,
          "type": "query"
        }
      ]
    },
    "time": {
      "from": "now-6h",
      "to": "now"
    },
    "timepicker": {},
    "timezone": "",
    "title": "Fluentd Deployment Alerts",
    "uid": "-FPV4csvLa7z",
    "version": 1,
    "weekStart": ""
  },
  "folderUid": "d4480be7-99b5-4c30-85ad-a79f79c08ce9",
  "overwrite": true
}
